sdg_flasher/__init__.py
sdg_flasher/__main__.py
sdg_flasher/test.py
sdg_flasher-0.8.dist-info/LICENSE
sdg_flasher-0.8.dist-info/METADATA
sdg_flasher-0.8.dist-info/WHEEL
sdg_flasher-0.8.dist-info/top_level.txt
sdg_flasher-0.8.dist-info/RECORD
