Metadata-Version: 2.1
Name: sdg-flasher
Version: 0.8
Summary: universal programmer for microcontrollers via bootloader
Author: chernecov_ev
Author-email: chernecov.ev@gmail.com
Classifier: Programming Language :: Python :: 3
Classifier: License :: OSI Approved :: MIT License
Classifier: Operating System :: OS Independent
Requires-Python: >=3.6
License-File: LICENSE
Requires-Dist: intelhex
Requires-Dist: sdg-dev >=2.0
Requires-Dist: sdg-io >=3.0
Requires-Dist: sdg-utils >=1.0
